cloudlib/__init__.py
cloudlib/account_utils.py
cloudlib/constants.py
cloudlib/datetime_helpers.py
cloudlib/exceptions.py
cloudlib/logging.py
cloudlib/metadata.py
cloudlib/package_management.py
cloudlib/roles.py
cloudlib/secrets.py
cloudboss_cloudlib-1.0.2.dist-info/METADATA
cloudboss_cloudlib-1.0.2.dist-info/WHEEL
cloudboss_cloudlib-1.0.2.dist-info/RECORD
