Metadata-Version: 2.1
Name: cloudboss-cloudlib
Version: 1.0.2
Summary: Python utils that are helpful for developing cloud applications
License: Proprietary
Author: Adam Varga
Author-email: adam.varga@cloudboss.hu
Requires-Python: >=3.10,<4.0
Classifier: License :: Other/Proprietary License
Classifier: Programming Language :: Python :: 3
Classifier: Programming Language :: Python :: 3.10
Classifier: Programming Language :: Python :: 3.11
Requires-Dist: boto3
